src/__init__.py
src/cli.py
src/embeddings.py
git_semantic_similarity-1.0.7.dist-info/LICENSE
git_semantic_similarity-1.0.7.dist-info/METADATA
git_semantic_similarity-1.0.7.dist-info/WHEEL
git_semantic_similarity-1.0.7.dist-info/entry_points.txt
git_semantic_similarity-1.0.7.dist-info/top_level.txt
git_semantic_similarity-1.0.7.dist-info/RECORD
