Metadata-Version: 2.2
Name: git-semantic-similarity
Version: 1.0.7
Summary: Search git commit messages by semantic similarity with embeddings from sentence-transformers.
License: MIT License
Classifier: Programming Language :: Python :: 3
Classifier: License :: OSI Approved :: MIT License
Classifier: Operating System :: OS Independent
Requires-Python: >=3.7
License-File: LICENSE
Requires-Dist: sentence_transformers==3.4.1
Requires-Dist: GitPython==3.1.44
Requires-Dist: numpy==2.2.3
Requires-Dist: click==8.1.8
Requires-Dist: tqdm==4.67.1
